{
  "breakpoints": {
    "375": {
      "name": "admin-layout-shell",
      "viewportWidth": 327,
      "width": 327,
      "height": 960,
      "bones": [
        [
          0,
          0,
          100,
          960,
          8,
          true
        ],
        [
          7.3394,
          24,
          68.5015,
          40,
          22
        ],
        [
          7.3394,
          88,
          85.3211,
          128,
          28
        ],
        [
          7.3394,
          232,
          85.3211,
          128,
          28
        ],
        [
          7.3394,
          376,
          85.3211,
          128,
          28
        ],
        [
          7.3394,
          520,
          85.3211,
          128,
          28
        ],
        [
          7.3394,
          664,
          85.3211,
          128,
          28
        ],
        [
          7.3394,
          808,
          85.3211,
          128,
          28
        ]
      ]
    },
    "768": {
      "name": "admin-layout-shell",
      "viewportWidth": 720,
      "width": 720,
      "height": 900,
      "bones": [
        [
          0,
          0,
          100,
          900,
          8,
          true
        ],
        [
          3.3333,
          24,
          31.1111,
          40,
          22
        ],
        [
          3.3333,
          88,
          45.5556,
          128,
          28
        ],
        [
          51.1111,
          88,
          45.5556,
          128,
          28
        ],
        [
          3.3333,
          232,
          45.5556,
          128,
          28
        ],
        [
          51.1111,
          232,
          45.5556,
          128,
          28
        ],
        [
          3.3333,
          376,
          45.5556,
          128,
          28
        ],
        [
          51.1111,
          376,
          45.5556,
          128,
          28
        ]
      ]
    },
    "1280": {
      "name": "admin-layout-shell",
      "viewportWidth": 1232,
      "width": 1232,
      "height": 900,
      "bones": [
        [
          0,
          0,
          100,
          900,
          8,
          true
        ],
        [
          0,
          0,
          20.7792,
          900,
          8,
          true
        ],
        [
          1.9481,
          12,
          3.2468,
          40,
          28
        ],
        [
          5.8442,
          20,
          7.7922,
          24,
          22
        ],
        [
          1.2987,
          80,
          18.1006,
          40,
          22
        ],
        [
          1.2987,
          128,
          18.1006,
          40,
          22
        ],
        [
          1.2987,
          176,
          18.1006,
          40,
          22
        ],
        [
          1.2987,
          224,
          18.1006,
          40,
          22
        ],
        [
          1.2987,
          272,
          18.1006,
          40,
          22
        ],
        [
          1.2987,
          320,
          18.1006,
          40,
          22
        ],
        [
          1.2987,
          368,
          18.1006,
          40,
          22
        ],
        [
          1.2987,
          416,
          18.1006,
          40,
          22
        ],
        [
          22.7273,
          24,
          18.1818,
          40,
          22
        ],
        [
          22.7273,
          88,
          24.2416,
          128,
          28
        ],
        [
          48.2676,
          88,
          24.2428,
          128,
          28
        ],
        [
          73.8091,
          88,
          24.2416,
          128,
          28
        ],
        [
          22.7273,
          232,
          24.2416,
          128,
          28
        ],
        [
          48.2676,
          232,
          24.2428,
          128,
          28
        ],
        [
          73.8091,
          232,
          24.2416,
          128,
          28
        ]
      ]
    }
  },
  "_hash": "9270b1483f4924c21506cb2f4a44240b"
}